xspline/__init__.py
xspline/bspl.py
xspline/indi.py
xspline/poly.py
xspline/typing.py
xspline/xfunction.py
xspline/xspl.py
xspline-0.1.1.dist-info/LICENSE
xspline-0.1.1.dist-info/METADATA
xspline-0.1.1.dist-info/WHEEL
xspline-0.1.1.dist-info/top_level.txt
xspline-0.1.1.dist-info/RECORD
