Metadata-Version: 2.1
Name: xspline
Version: 0.1.1
Summary: Advanced spline package that provides b-spline bases, their derivatives and integrals
Author-email: IHME Math Sciences <ihme.math.sciences@gmail.com>
License: BSD 2-Clause
Project-URL: github, https://github.com/ihmeuw-msca/xspline
Requires-Python: >=3.10
License-File: LICENSE
Requires-Dist: numpy >=1.25.1
Provides-Extra: docs
Requires-Dist: sphinx ; extra == 'docs'
Requires-Dist: sphinx-autodoc-typehints ; extra == 'docs'
Requires-Dist: furo ; extra == 'docs'
Provides-Extra: test
Requires-Dist: pytest ; extra == 'test'
Requires-Dist: pytest-cov ; extra == 'test'
